{
	"name": "ಸಳ, ಹೊಯ್ಸಳ (೧೦೦೬)",
	"children": [
		{
			"name": "ವಿನಯಾಾದಿತ್ಯ, ತ್ರಿಭುವನಮಲ್ಲ - ಹೊಯ್ಸಳ (೧೦೪೭ - ೧೧೦೦)",
			"children": [
				{
					"name": "ಎರೆಯಂಗ, ಯುವರಾಜ (೧೦೬೩ - ೧೧೦೦)",
					"children": [
						{
							"name": "ಬಲ್ಲಾಳ - ೧ (೧೧೦೧ - ೧೧೦೯)",
							"children": [
								{
									"name": "ನರಸಿಂಹ - ೧, ಪ್ರತಾಪನರಸಿಂಹ (೧೧೪೧ - ೧೧೭೩)",
									"children": [
										{
											"name": "ಬಲ್ಲಾಳ - ೨, ವೀರಬಲ್ಲಾಳ, ಶನಿವಾರಸಿದ್ಧಿ, ಗಿರಿದುರ್ಗಮಲ್ಲ, ಯಾದವನಾರಾಯಣ (೧೧೭೩ - ೧೨೨೦)",
											"children": [
												{
													"name": "ನರಸಿಂಹ - ೨, ವೀರನರಸಿಂಹ (೧೨೨೦ - ೧೨೩೫) ",
													"children": [
														{
															"name": "ಸೋಮೇಶ್ವರ, ವೀರಸೋಮೇಶ್ವರ (೧೨೫೩ - ೧೨೫೪)",
															"children": [
																{
																	"name": "ನರಸಿಂಹ - ೩, ವೀರನರಸಿಂಹ (೧೨೫೪ - ೧೨೭೧)",
																	"children": [
																		{
																			"name": "ಬಲ್ಲಾಳ - ೩, ವೀರಬಲ್ಲಾಳ (೧೨೭೧ - ೧೩೪೨)",
																			"children": [
																				{
																					"name": "ಬಲ್ಲಾಳ - ೪ (೧೩೪೩)"
																				}
																			]
																		}
																	]
																}
															]
														}
													]
												}
											]
										}
									]
								}
							]
						},
						{
							"name": "ಬಿಟ್ಟಿದೇವ, ವಿಷ್ಣುವರ್ಧನ (೧೧೧೧ - ೧೧೭೩)"
						}
					]
				}
			]
		}
	]
}